ai_helpers_meena/__init__.py
ai_helpers_meena/client.py
ai_helpers_meena/utils.py
ai_helpers_meena-0.1.0.dist-info/METADATA
ai_helpers_meena-0.1.0.dist-info/WHEEL
ai_helpers_meena-0.1.0.dist-info/top_level.txt
ai_helpers_meena-0.1.0.dist-info/RECORD
