Metadata-Version: 2.4
Name: ai-helpers-meena
Version: 0.1.0
Summary: A simple AI helper library for text processing.
Author-email: Meena <your-email@example.com>
License: MIT License
Project-URL: Homepage, https://pypi.org/project/ai-helpers-meena/
Requires-Python: >=3.8
